CHANGELOG.md
tracerepo/__init__.py
tracerepo/__main__.py
tracerepo/cli.py
tracerepo/organize.py
tracerepo/repo.py
tracerepo/rules.py
tracerepo/schema_checks.py
tracerepo/spatial.py
tracerepo/trace_schema.py
tracerepo/utils.py
tracerepo-0.0.7.dist-info/entry_points.txt
tracerepo-0.0.7.dist-info/WHEEL
tracerepo-0.0.7.dist-info/METADATA
tracerepo-0.0.7.dist-info/RECORD
