Metadata-Version: 2.1
Name: tracerepo
Version: 0.0.7
Summary: Fracture & lineament data management.
Home-page: https://github.com/nialov/tracerepo
License: MIT
Keywords: data,gis,geology,fracture,topology
Author: nialov
Author-email: nikolasovaskainen@gmail.com
Requires-Python: >=3.7.1,<4.0.0
Classifier: Development Status :: 4 - Beta
Classifier: Intended Audience :: Science/Research
Classifier: License :: OSI Approved :: MIT License
Classifier: Programming Language :: Python :: 3
Classifier: Programming Language :: Python :: 3 :: Only
Classifier: Programming Language :: Python :: 3.10
Classifier: Programming Language :: Python :: 3.8
Classifier: Programming Language :: Python :: 3.9
Classifier: Topic :: Scientific/Engineering :: GIS
Provides-Extra: coverage
Provides-Extra: docs
Provides-Extra: format-lint
Provides-Extra: typecheck
Requires-Dist: black[jupyter]; extra == "format-lint"
Requires-Dist: blackdoc; extra == "format-lint"
Requires-Dist: blacken-docs; extra == "format-lint"
Requires-Dist: coverage (>=5.0,<6.0); extra == "coverage"
Requires-Dist: coverage-badge; extra == "coverage"
Requires-Dist: fractopo (>=0.3.0,<0.4.0)
Requires-Dist: isort; extra == "format-lint"
Requires-Dist: json5 (>=0.9.6,<0.10.0)
Requires-Dist: mypy; extra == "typecheck"
Requires-Dist: nbsphinx; extra == "docs"
Requires-Dist: nialog (>=0.0.1,<0.0.2)
Requires-Dist: pandas
Requires-Dist: pandera
Requires-Dist: pydantic (>=1.8.2,<2.0.0)
Requires-Dist: pylint; extra == "format-lint"
Requires-Dist: pyproj (>=3.1,<3.2)
Requires-Dist: rich
Requires-Dist: rstcheck; extra == "format-lint"
Requires-Dist: sphinx-autobuild; extra == "docs"
Requires-Dist: sphinx-autodoc-typehints; extra == "docs"
Requires-Dist: sphinx-gallery; extra == "docs"
Requires-Dist: sphinx-rtd-theme; extra == "docs"
Requires-Dist: sphinx; extra == "docs" or extra == "format-lint"
Requires-Dist: typer
Project-URL: Documentation, https://tracerepo.readthedocs.io/en/latest/
Project-URL: Repository, https://github.com/nialov/tracerepo
